chalice_veneer/__init__.py
chalice_veneer/openapi_schema.py
chalice_veneer/route.py
chalice_veneer/service.py
chalice_veneer/service_blueprint.py
chalice_veneer-0.0.28.dist-info/LICENSE
chalice_veneer-0.0.28.dist-info/METADATA
chalice_veneer-0.0.28.dist-info/WHEEL
chalice_veneer-0.0.28.dist-info/top_level.txt
chalice_veneer-0.0.28.dist-info/RECORD
