Metadata-Version: 2.1
Name: chalice-veneer
Version: 0.0.28
Summary: Class based routing for Chalice with built in validation through Pydantic
Home-page: https://github.com/KristaBliss/chalice-veneer
Author: Krista Bliss
Author-email: contact@kristabliss.com
License: MIT
Platform: UNKNOWN
Classifier: Development Status :: 4 - Beta
Classifier: Intended Audience :: Developers
Classifier: License :: OSI Approved :: MIT License
Classifier: Programming Language :: Python :: 3 :: Only
Classifier: Programming Language :: Python :: 3.7
Classifier: Programming Language :: Python :: 3.8
Classifier: Programming Language :: Python :: 3.9
Classifier: Programming Language :: Python :: 3.10
Requires-Python: >=3.7
License-File: LICENSE
Requires-Dist: pydantic
Requires-Dist: openapi-schema-pydantic
